aiosteam_api/__init__.py
aiosteam_api/steam.py
aiosteam_api/clients/__init__.py
aiosteam_api/clients/requests_client.py
aiosteam_api/clients/utils.py
aiosteam_api/exceptions/__init__.py
aiosteam_api/exceptions/api_errors.py
aiosteam_api/steam_models/__init__.py
aiosteam_api/steam_models/badges.py
aiosteam_api/steam_models/games.py
aiosteam_api/steam_models/user.py
aiosteam_api-1.1.7.dist-info/LICENCE
aiosteam_api-1.1.7.dist-info/METADATA
aiosteam_api-1.1.7.dist-info/WHEEL
aiosteam_api-1.1.7.dist-info/top_level.txt
aiosteam_api-1.1.7.dist-info/RECORD
