Metadata-Version: 2.1
Name: aiosteam-api
Version: 1.1.7
Summary: Async Python Client wrapper for Steam API
Home-page: https://github.com/jgavrus/aiosteam-api
Author: Yevhenii Havrus
Author-email: jeygavrus@gmail.com
License: MIT
Keywords: async steam,steam api,async steam community,api,async
Classifier: Development Status :: 4 - Beta
Classifier: Intended Audience :: Developers
Classifier: License :: OSI Approved :: MIT License
Classifier: Operating System :: OS Independent
Classifier: Programming Language :: Python :: 3
Classifier: Programming Language :: Python :: 3.10
Classifier: Programming Language :: Python :: 3.11
Classifier: Programming Language :: Python
License-File: LICENCE
Requires-Dist: beautifulsoup4
Requires-Dist: aiohttp
Requires-Dist: pydantic
